codeqai/__init__.py
codeqai/__main__.py
codeqai/app.py
codeqai/bootstrap.py
codeqai/cache.py
codeqai/codeparser.py
codeqai/config.py
codeqai/constants.py
codeqai/dataset-extractor.py
codeqai/distillation.py
codeqai/embeddings.py
codeqai/llm.py
codeqai/repo.py
codeqai/streamlit.py
codeqai/treesitter/__init__.py
codeqai/treesitter/treesitter.py
codeqai/treesitter/treesitter_c.py
codeqai/treesitter/treesitter_cpp.py
codeqai/treesitter/treesitter_cs.py
codeqai/treesitter/treesitter_go.py
codeqai/treesitter/treesitter_hs.py
codeqai/treesitter/treesitter_java.py
codeqai/treesitter/treesitter_js.py
codeqai/treesitter/treesitter_kt.py
codeqai/treesitter/treesitter_py.py
codeqai/treesitter/treesitter_rb.py
codeqai/treesitter/treesitter_registry.py
codeqai/treesitter/treesitter_rs.py
codeqai/treesitter/treesitter_ts.py
codeqai/utils.py
codeqai/vector_store.py
codeqai-0.0.19.dist-info/LICENSE
codeqai-0.0.19.dist-info/METADATA
codeqai-0.0.19.dist-info/WHEEL
codeqai-0.0.19.dist-info/entry_points.txt
codeqai-0.0.19.dist-info/RECORD
