Metadata-Version: 2.3
Name: codeqai
Version: 0.0.19
Summary: 
Author: fynnfluegge
Author-email: fynnfluegge@gmx.de
Requires-Python: >=3.9, !=2.7.*, !=3.0.*, !=3.1.*, !=3.2.*, !=3.3.*, !=3.4.*, !=3.5.*, !=3.6.*, !=3.7.*, !=3.8.*, !=3.12.*, !=3.13.*
Classifier: Programming Language :: Python :: 3
Classifier: Programming Language :: Python :: 3.9
Classifier: Programming Language :: Python :: 3.10
Classifier: Programming Language :: Python :: 3.11
Requires-Dist: click (>=8.1.7,<9.0.0)
Requires-Dist: gitpython (>=3.1.36,<4.0.0)
Requires-Dist: inquirer (>=3.1.3,<4.0.0)
Requires-Dist: langchain (>=0.1.5,<0.2.0)
Requires-Dist: langchain-anthropic (>=0.1.8,<0.2.0)
Requires-Dist: langchain-community (>=0.0.32,<0.0.33)
Requires-Dist: langchain-core (>=0.1.42,<0.2.0)
Requires-Dist: langchain-openai (>=0.0.5,<0.0.6)
Requires-Dist: openai (>=1.11.1,<2.0.0)
Requires-Dist: python-dotenv (>=1.0.0,<2.0.0)
Requires-Dist: pyyaml (>=6.0.1,<7.0.0)
Requires-Dist: rich (>=13.5.3,<14.0.0)
Requires-Dist: streamlit (>=1.31.0,<2.0.0)
Requires-Dist: tiktoken (>=0.5.2,<0.6.0)
Requires-Dist: tree-sitter (>=0.20.2,<0.21.0)
Requires-Dist: tree-sitter-languages (>=1.7.0,<2.0.0)
Requires-Dist: yaspin (>=3.0.0,<4.0.0)
